avrzero/__init__.py
avrzero/__main__.py
avrzero/assembler.py
avrzero/error.py
avrzero/formatter.py
avrzero/gui.py
avrzero/instruction.py
avrzero/machine.py
avrzero/register.py
avrzero/variable.py
avrzero/example/times_two.asm
avrzero-0.0.3.dist-info/METADATA
avrzero-0.0.3.dist-info/WHEEL
avrzero-0.0.3.dist-info/licenses/LICENSE
avrzero-0.0.3.dist-info/RECORD
