Metadata-Version: 2.1
Name: avrzero
Version: 0.0.3
Summary: A simple AVR instruction set simulator for educational purposes.
Project-URL: Homepage, https://github.com/Edward-Ji/AVRZero
Project-URL: Bug Tracker, https://github.com/Edward-Ji/AVRZero/issues
Author-email: Edward Ji <jiziao6@gmail.com>
License-File: LICENSE
Classifier: License :: OSI Approved :: MIT License
Classifier: Operating System :: OS Independent
Classifier: Programming Language :: Python :: 3
Requires-Python: >=3.7
